investimentos/__init__.py
investimentos/investimentos.py
teste_stransky-0.4.dist-info/LICENSE
teste_stransky-0.4.dist-info/METADATA
teste_stransky-0.4.dist-info/WHEEL
teste_stransky-0.4.dist-info/top_level.txt
teste_stransky-0.4.dist-info/RECORD
