Metadata-Version: 2.1
Name: teste-stransky
Version: 0.4
Summary: Uma biblioteca para cálculos de investimentos. Simulador de investimentos para estudos
Home-page: https://github.com/marcelostransky/meu_investimento
Author: Marcelo Stransky
Author-email: marcelostransky@gmail.com
Classifier: Programming Language :: Python :: 3
Classifier: License :: OSI Approved :: MIT License
Classifier: Operating System :: OS Independent
Requires-Python: >=3.6
License-File: LICENSE
